pragati/__init__.py
pragati-1.19.dist-info/METADATA
pragati-1.19.dist-info/WHEEL
pragati-1.19.dist-info/top_level.txt
pragati-1.19.dist-info/RECORD
