Metadata-Version: 2.1
Name: pragati
Version: 1.19
Summary: a pragati module 
Home-page: UNKNOWN
Author: The Garbage Minded Man
License: UNKNOWN
Keywords: Garbage,Guido Van Rossum
Platform: UNKNOWN
Classifier: Intended Audience :: Developers
Classifier: Programming Language :: Python :: 3
Classifier: Operating System :: Unix
Classifier: Operating System :: MacOS
Classifier: Operating System :: Microsoft :: Windows
